tsvtools/__init__.py
tsvtools/_version.py
tsvtools/libs.py
tsvtools/tab_filter.py
tsvtools/tab_merge.py
tsvtools/tab_reorder.py
tsvtools/tab_tag.py
tsvtools/tab_view.py
tsvtools-0.2.0.data/scripts/cols
tsvtools-0.2.0.data/scripts/tsv
tsvtools-0.2.0.data/scripts/tsvtools
tsvtools-0.2.0.dist-info/LICENSE
tsvtools-0.2.0.dist-info/METADATA
tsvtools-0.2.0.dist-info/WHEEL
tsvtools-0.2.0.dist-info/top_level.txt
tsvtools-0.2.0.dist-info/RECORD
